README.rst
setup.cfg
setup.py
touchberrypi/__init__.py
touchberrypi/accelerometer.py
touchberrypi/color.py
touchberrypi/i2c_peripheral.py
touchberrypi/leds.py
touchberrypi/temperature_sensor.py
touchberrypi/touch_sensor.py
touchberrypi/touchberry_pi.py
touchberrypi.egg-info/PKG-INFO
touchberrypi.egg-info/SOURCES.txt
touchberrypi.egg-info/dependency_links.txt
touchberrypi.egg-info/requires.txt
touchberrypi.egg-info/top_level.txt