Metadata-Version: 1.2
Name: touchberrypi
Version: 0.2.0
Summary: Python library and driver for the Touchberry Pi v2.0 Hat for the Raspberry Pi
Home-page: https://github.com/sillevl/python-touchberrypi
Author: Sille Van Landschoot, Nico De Witte
Author-email: info@sillevl.be
License: MIT
Keywords: raspberrypi touchberrypi touch leds temperature sensor
Platform: UNKNOWN
Classifier: Development Status :: 2 - Pre-Alpha
Classifier: Intended Audience :: Developers
Classifier: Topic :: Software Development
Classifier: License :: OSI Approved :: MIT License
Classifier: Programming Language :: Python :: 3
Classifier: Programming Language :: Python :: 3.3
Classifier: Programming Language :: Python :: 3.4
Classifier: Programming Language :: Python :: 3.5
Requires-Python: >=3
